iospy/__init__.py
iospy/__main__.py
iospy/mobilesync.py
iospy/util.py
iOSpy-0.2.0.dist-info/METADATA
iOSpy-0.2.0.dist-info/WHEEL
iOSpy-0.2.0.dist-info/entry_points.txt
iOSpy-0.2.0.dist-info/top_level.txt
iOSpy-0.2.0.dist-info/RECORD
