Metadata-Version: 2.1
Name: iOSpy
Version: 0.2.0
Summary: iOS MobileSync backup data extraction
Home-page: https://github.com/chbrown/iOSpy
Author: Christopher Brown
Author-email: io@henrian.com
License: MIT
Platform: UNKNOWN
Requires-Python: >=3.6
Requires-Dist: appdirs (>=1.4.0)
Requires-Dist: click (>=7.0)
Requires-Dist: file-magic (>=0.4.0)
